tap_freshservice/__init__.py
tap_freshservice/client.py
tap_freshservice/paginator.py
tap_freshservice/streams/agents.py
tap_freshservice/streams/asset_requests.py
tap_freshservice/streams/asset_types.py
tap_freshservice/streams/assets.py
tap_freshservice/streams/departments.py
tap_freshservice/streams/groups.py
tap_freshservice/streams/locations.py
tap_freshservice/streams/requesters.py
tap_freshservice/streams/ticket_activities.py
tap_freshservice/streams/tickets.py
tap_freshservice/streams/time_entries.py
tap_freshservice/tap.py
tap_freshservice-0.11.0.dist-info/LICENSE
tap_freshservice-0.11.0.dist-info/METADATA
tap_freshservice-0.11.0.dist-info/WHEEL
tap_freshservice-0.11.0.dist-info/entry_points.txt
tap_freshservice-0.11.0.dist-info/RECORD
